eggplant/__init__.py
eggplant/constants.py
eggplant/flycheck_methods.py
eggplant/flycheck_models.py
eggplant/flycheck_preprocess.py
eggplant/flycheck_utils.py
eggplant/methods.py
eggplant/models.py
eggplant/ode.py
eggplant/plot.py
eggplant/preprocess.py
eggplant/sdea.py
eggplant/utils.py
test/__init__.py
test/test_methods.py
test/test_model.py
test/test_plot.py
test/test_preprocess.py
test/test_sdea.py
test/test_utils.py
test/utils.py
spatial_eggplant-0.2.3.dist-info/LICENSE
spatial_eggplant-0.2.3.dist-info/METADATA
spatial_eggplant-0.2.3.dist-info/WHEEL
spatial_eggplant-0.2.3.dist-info/top_level.txt
spatial_eggplant-0.2.3.dist-info/RECORD
