Metadata-Version: 2.1
Name: spatial-eggplant
Version: 0.2.3
Summary: Landmark-based transfer of spatial transcriptomics data
Home-page: https://github.com/almaan/eggplant
Author: Alma Andersson
Author-email: almaan@kth.se
License: UNKNOWN
Platform: UNKNOWN
Classifier: Programming Language :: Python :: 3.7
Classifier: License :: OSI Approved :: MIT License
Classifier: Natural Language :: English
Classifier: Operating System :: POSIX :: Linux
Requires-Python: >=3.7
Requires-Dist: numpy (<=1.20,>1.19)
Requires-Dist: numba
Requires-Dist: pandas (>=1.0.0)
Requires-Dist: anndata (>=0.7.5)
Requires-Dist: matplotlib (>=3.3.3)
Requires-Dist: scanpy (>=1.5.0)
Requires-Dist: torch (>=1.8.1)
Requires-Dist: gpytorch (>=1.4.2)
Requires-Dist: squidpy (>=1.1.0)
Requires-Dist: morphops (>=0.1.12)
Requires-Dist: tqdm
Requires-Dist: scipy
Requires-Dist: kneed
Provides-Extra: dev
Requires-Dist: pre-commit (>=2.9.0) ; extra == 'dev'
